autodistill_segment_anything/__init__.py
autodistill_segment_anything/sam_model.py
autodistill_segment_anything-0.1.1.dist-info/LICENSE
autodistill_segment_anything-0.1.1.dist-info/METADATA
autodistill_segment_anything-0.1.1.dist-info/WHEEL
autodistill_segment_anything-0.1.1.dist-info/top_level.txt
autodistill_segment_anything-0.1.1.dist-info/RECORD
