Metadata-Version: 2.1
Name: autodistill-segment-anything
Version: 0.1.1
Summary: Segment Anything model for use with Autodistill
Home-page: https://github.com/autodistill/autodistill-segment-anything
Author: Roboflow
Author-email: support@roboflow.com
Classifier: Programming Language :: Python :: 3
Classifier: License :: OSI Approved :: MIT License
Classifier: Operating System :: OS Independent
Requires-Python: >=3.7
License-File: LICENSE
Requires-Dist: torch
Requires-Dist: autodistill
Requires-Dist: numpy >=1.20.0
Requires-Dist: opencv-python >=4.6.0
Requires-Dist: rf-groundingdino
Requires-Dist: rf-segment-anything
Requires-Dist: supervision
Requires-Dist: autodistill-grounded-sam
Provides-Extra: dev
Requires-Dist: flake8 ; extra == 'dev'
Requires-Dist: black ==22.3.0 ; extra == 'dev'
Requires-Dist: isort ; extra == 'dev'
Requires-Dist: twine ; extra == 'dev'
Requires-Dist: pytest ; extra == 'dev'
Requires-Dist: wheel ; extra == 'dev'
